[{"recipe_ID": "214896", " Per Serving Calories": " 240 "}, {"recipe_ID": "13227", " Per Serving Calories": " 502 "}, {"recipe_ID": "13430", " Per Serving Calories": " 455 "}, {"recipe_ID": "17826", " Per Serving Calories": " 630 "}, {"recipe_ID": "233431", " Per Serving Calories": " 272 "}, {"recipe_ID": "53465", " Per Serving Calories": " 389 "}, {"recipe_ID": "17534", " Per Serving Calories": " 520 "}, {"recipe_ID": "203789", " Per Serving Calories": " 533 "}, {"recipe_ID": "166139", " Per Serving Calories": " 289 "}, {"recipe_ID": "234177", " Per Serving Calories": " 242 "}, {"recipe_ID": "255989", " Per Serving Calories": " 693 "}, {"recipe_ID": "270920", " Per Serving Calories": " 356 "}, {"recipe_ID": "187504", " Per Serving Calories": " 195 "}, {"recipe_ID": "268963", " Per Serving Calories": " 353 "}, {"recipe_ID": "45840", " Per Serving Calories": " 320 "}, {"recipe_ID": "262301", " Per Serving Calories": " 233 "}, {"recipe_ID": "13264", " Per Serving Calories": " 217 "}, {"recipe_ID": "276974", " Per Serving Calories": " 221 "}, {"recipe_ID": "257061", " Per Serving Calories": " 408 "}, {"recipe_ID": "269407", " Per Serving Calories": " 307 "}, {"recipe_ID": "230154", " Per Serving Calories": " 344 "}, {"recipe_ID": "17608", " Per Serving Calories": " 168 "}, {"recipe_ID": "276975", " Per Serving Calories": " 226 "}, {"recipe_ID": "260557"}, {"recipe_ID": "13055", " Per Serving Calories": " 564 "}, {"recipe_ID": "12995", " Per Serving Calories": " 389 "}, {"recipe_ID": "258179", " Per Serving Calories": " 720 "}, {"recipe_ID": "255269", " Per Serving Calories": " 455 "}, {"recipe_ID": "45048", " Per Serving Calories": " 396 "}, {"recipe_ID": "262299", " Per Serving Calories": " 425 "}, {"recipe_ID": "15688", " Per Serving Calories": " 370 "}, {"recipe_ID": "73022", " Per Serving Calories": " 294 "}, {"recipe_ID": "228385", " Per Serving Calories": " 484 "}, {"recipe_ID": "72559", " Per Serving Calories": " 233 "}, {"recipe_ID": "270425"}, {"recipe_ID": "15342", " Per Serving Calories": " 651 "}, {"recipe_ID": "276697"}, {"recipe_ID": "98595", " Per Serving Calories": " 375 "}, {"recipe_ID": "59343", " Per Serving Calories": " 347 "}, {"recipe_ID": "238633", " Per Serving Calories": " 428 "}, {"recipe_ID": "262302", " Per Serving Calories": " 393 "}, {"recipe_ID": "233819", " Per Serving Calories": " 403 "}, {"recipe_ID": "276973", " Per Serving Calories": " 198 "}, {"recipe_ID": "260830"}, {"recipe_ID": "84013", " Per Serving Calories": " 284 "}, {"recipe_ID": "266539", " Per Serving Calories": " 289 "}, {"recipe_ID": "26671", " Per Serving Calories": " 434 "}, {"recipe_ID": "18084", " Per Serving Calories": " 347 "}, {"recipe_ID": "237558", " Per Serving Calories": " 475 "}, {"recipe_ID": "68540", " Per Serving Calories": " 227 "}, {"recipe_ID": "255268", " Per Serving Calories": " 562 "}, {"recipe_ID": "217838", " Per Serving Calories": " 636 "}, {"recipe_ID": "216090", " Per Serving Calories": " 365 "}, {"recipe_ID": "223510", " Per Serving Calories": " 440 "}, {"recipe_ID": "12951", " Per Serving Calories": " 587 "}, {"recipe_ID": "22491", " Per Serving Calories": " 426 "}, {"recipe_ID": "245278", " Per Serving Calories": " 179 "}, {"recipe_ID": "258251", " Per Serving Calories": " 467 "}, {"recipe_ID": "278163"}, {"recipe_ID": "159164", " Per Serving Calories": " 160 "}, {"recipe_ID": "19782", " Per Serving Calories": " 300 "}, {"recipe_ID": "262320", " Per Serving Calories": " 248 "}, {"recipe_ID": "270130"}, {"recipe_ID": "270590"}, {"recipe_ID": "139494", " Per Serving Calories": " 184 "}, {"recipe_ID": "76929"}, {"recipe_ID": "146089", " Per Serving Calories": " 488 "}, {"recipe_ID": "17211", " Per Serving Calories": " 471 "}, {"recipe_ID": "13428", " Per Serving Calories": " 89 "}, {"recipe_ID": "262317", " Per Serving Calories": " 217 "}, {"recipe_ID": "13073", " Per Serving Calories": " 299 "}, {"recipe_ID": "13274", " Per Serving Calories": " 539 "}, {"recipe_ID": "15166", " Per Serving Calories": " 977 "}, {"recipe_ID": "245279", " Per Serving Calories": " 239 "}, {"recipe_ID": "262321"}, {"recipe_ID": "13441", " Per Serving Calories": " 748 "}, {"recipe_ID": "232327", " Per Serving Calories": " 303 "}, {"recipe_ID": "276527", " Per Serving Calories": " 388 "}, {"recipe_ID": "13330", " Per Serving Calories": " 235 "}, {"recipe_ID": "149388", " Per Serving Calories": " 177 "}, {"recipe_ID": "236436", " Per Serving Calories": " 454 "}, {"recipe_ID": "278357", " Per Serving Calories": " 514 "}, {"recipe_ID": "237635", " Per Serving Calories": " 208 "}, {"recipe_ID": "17490", " Per Serving Calories": " 219 "}, {"recipe_ID": "262303", " Per Serving Calories": " 387 "}, {"recipe_ID": "267913", " Per Serving Calories": " 529 "}, {"recipe_ID": "13969", " Per Serving Calories": " 391 "}, {"recipe_ID": "275209", " Per Serving Calories": " 315 "}, {"recipe_ID": "16826", " Per Serving Calories": " 374 "}, {"recipe_ID": "232444", " Per Serving Calories": " 420 "}, {"recipe_ID": "234712", " Per Serving Calories": " 200 "}, {"recipe_ID": "126388", " Per Serving Calories": " 402 "}, {"recipe_ID": "277371", " Per Serving Calories": " 344 "}, {"recipe_ID": "262297", " Per Serving Calories": " 231 "}, {"recipe_ID": "262295", " Per Serving Calories": " 404 "}, {"recipe_ID": "207823", " Per Serving Calories": " 395 "}, {"recipe_ID": "222096", " Per Serving Calories": " 208 "}, {"recipe_ID": "214167", " Per Serving Calories": " 326 "}, {"recipe_ID": "236923", " Per Serving Calories": " 368 "}, {"recipe_ID": "236508", " Per Serving Calories": " 242 "}, {"recipe_ID": "263422", " Per Serving Calories": " 851 "}, {"recipe_ID": "256858", " Per Serving Calories": " 626 "}, {"recipe_ID": "237433", " Per Serving Calories": " 259 "}, {"recipe_ID": "239496", " Per Serving Calories": " 327 "}, {"recipe_ID": "276982", " Per Serving Calories": " 502 "}, {"recipe_ID": "275475", " Per Serving Calories": " 205 "}, {"recipe_ID": "274970"}, {"recipe_ID": "267901", " Per Serving Calories": " 365 "}, {"recipe_ID": "73139", " Per Serving Calories": " 347 "}, {"recipe_ID": "278860", " Per Serving Calories": " 262 "}, {"recipe_ID": "13019", " Per Serving Calories": " 367 "}, {"recipe_ID": "280443", " Per Serving Calories": " 178 "}, {"recipe_ID": "15343", " Per Serving Calories": " 296 "}, {"recipe_ID": "13032", " Per Serving Calories": " 669 "}, {"recipe_ID": "164555", " Per Serving Calories": " 299 "}, {"recipe_ID": "15043", " Per Serving Calories": " 257 "}, {"recipe_ID": "77522", " Per Serving Calories": " 178 "}, {"recipe_ID": "188390", " Per Serving Calories": " 143 "}, {"recipe_ID": "262306", " Per Serving Calories": " 322 "}, {"recipe_ID": "15553", " Per Serving Calories": " 852 "}, {"recipe_ID": "23145", " Per Serving Calories": " 242 "}, {"recipe_ID": "216076", " Per Serving Calories": " 588 "}, {"recipe_ID": "256857", " Per Serving Calories": " 369 "}, {"recipe_ID": "278810"}, {"recipe_ID": "238099", " Per Serving Calories": " 303 "}, {"recipe_ID": "223268", " Per Serving Calories": " 407 "}, {"recipe_ID": "18050", " Per Serving Calories": " 489 "}, {"recipe_ID": "16673", " Per Serving Calories": " 401 "}, {"recipe_ID": "17544", " Per Serving Calories": " 143 "}, {"recipe_ID": "13367", " Per Serving Calories": " 418 "}, {"recipe_ID": "15273", " Per Serving Calories": " 359 "}, {"recipe_ID": "272664", " Per Serving Calories": " 323 "}, {"recipe_ID": "237014", " Per Serving Calories": " 229 "}, {"recipe_ID": "214090", " Per Serving Calories": " 503 "}]