[{"recipe_ID": "77107", " Per Serving Calories": " 262 "}, {"recipe_ID": "220872", " Per Serving Calories": " 341 "}, {"recipe_ID": "261972", " Per Serving Calories": " 452 "}, {"recipe_ID": "278628", " Per Serving Calories": " 178 "}, {"recipe_ID": "232323", " Per Serving Calories": " 370 "}, {"recipe_ID": "218545", " Per Serving Calories": " 331 "}, {"recipe_ID": "103054", " Per Serving Calories": " 291 "}, {"recipe_ID": "270134", " Per Serving Calories": " 178 "}, {"recipe_ID": "141361", " Per Serving Calories": " 635 "}, {"recipe_ID": "217106", " Per Serving Calories": " 415 "}, {"recipe_ID": "18776", " Per Serving Calories": " 495 "}, {"recipe_ID": "149184", " Per Serving Calories": " 478 "}, {"recipe_ID": "229326", " Per Serving Calories": " 238 "}, {"recipe_ID": "264662", " Per Serving Calories": " 208 "}, {"recipe_ID": "212616", " Per Serving Calories": " 687 "}, {"recipe_ID": "219062", " Per Serving Calories": " 523 "}, {"recipe_ID": "22335", " Per Serving Calories": " 281 "}, {"recipe_ID": "279384", " Per Serving Calories": " 266 "}, {"recipe_ID": "259151", " Per Serving Calories": " 236 "}, {"recipe_ID": "232301", " Per Serving Calories": " 376 "}, {"recipe_ID": "26827", " Per Serving Calories": " 110 "}, {"recipe_ID": "213760", " Per Serving Calories": " 149 "}, {"recipe_ID": "216614", " Per Serving Calories": " 492 "}, {"recipe_ID": "45368", " Per Serving Calories": " 320 "}]